[{"date":"2020-12-08T17:09","name":"alena1.jpg","size":278728,"mimetype":"image/jpeg","description":"Alena 1"},{"date":"2020-12-08T17:09","name":"alena2.jpg","size":505917,"mimetype":"image/jpeg","description":"Alena 2"},{"date":"2020-12-08T17:09","name":"alena3.jpg","size":614890,"mimetype":"image/jpeg","description":"Alena 3"},{"date":"2020-12-08T17:09","name":"alena4.jpg","size":912556,"mimetype":"image/jpeg","description":"Alena 4"},{"date":"2020-12-08T17:09","name":"alena5.jpg","size":409785,"mimetype":"image/jpeg","description":"Alena 5"},{"date":"2020-12-09T09:10","name":"apple_1.jpg","size":309226,"mimetype":"image/jpeg","description":"A"}]
